{ 
   "resource_type":"Infra",
   "children":[ 
      { 
         "resource_type":"ChildTier1",
         "marked_for_delete":true,
         "Tier1":{ 
            "resource_type":"Tier1",
            "id":"JenkinsAPP01-T1",
            "description":"JenkinsAPP01-T1",
            "display_name":"JenkinsAPP01-T1",
            "failover_mode":"NON_PREEMPTIVE",
            "tier0_path":"/infra/tier-0s/t0",
            "children":[ 
               { 
                  "resource_type":"ChildLocaleServices",
                  "LocaleServices":{ 
                     "resource_type":"LocaleServices",
                     "id":"default",
                     "edge_cluster_path":"/infra/sites/default/enforcement-points/default/edge-clusters/ff829166-fc3a-4b6c-a5d6-3d8d9ecd2dd7"
                  }
               },
               { 
                  "resource_type":"ChildSegment",
                  "Segment":{ 
                     "resource_type":"Segment",
                     "id":"JenkinsAPP01-web",
                     "description":"overlay web logical switch",
                     "display_name":"JenkinsAPP01-WEB",
                     "transport_zone_path":"/infra/sites/default/enforcement-points/default/transport-zones/1b3a2f36-bfd1-443e-a0f6-4de01abc963e",
                     "subnets":[ 
                        { 
                           "gateway_address":"172.16.211.1/24"
                        }
                     ]
                  }
               },
               { 
                  "resource_type":"ChildSegment",
                  "Segment":{ 
                     "resource_type":"Segment",
                     "id":"JenkinsAPP01-app",
                     "description":"overlay app logical switch",
                     "display_name":"JenkinsAPP01-APP",
                     "transport_zone_path":"/infra/sites/default/enforcement-points/default/transport-zones/1b3a2f36-bfd1-443e-a0f6-4de01abc963e",
                     "subnets":[ 
                        { 
                           "gateway_address":"172.16.212.1/24"
                        }
                     ]
                  }
               },
               { 
                  "resource_type":"ChildSegment",
                  "Segment":{ 
                     "resource_type":"Segment",
                     "id":"JenkinsAPP01-db",
                     "description":"overlay db logical switch",
                     "display_name":"JenkinsAPP01-DB",
                     "transport_zone_path":"/infra/sites/default/enforcement-points/default/transport-zones/1b3a2f36-bfd1-443e-a0f6-4de01abc963e",
                     "subnets":[ 
                        { 
                           "gateway_address":"172.16.213.1/24"
                        }
                     ]
                  }
               }
            ]
         }
      },
      { 
         "resource_type":"ChildService",
         "marked_for_delete":true,
         "Service":{ 
            "service_entries":[ 
               { 
                  "l4_protocol":"TCP",
                  "source_ports":[ 

                  ],
                  "destination_ports":[ 
                     "8443"
                  ],
                  "resource_type":"L4PortSetServiceEntry",
                  "id":"tcp_8443",
                  "display_name":"TCP 8443"
               }
            ],
            "resource_type":"Service",
            "id":"tcp_8443",
            "display_name":"tcp_8443"
         }
      },
      { 
         "resource_type":"ChildDomain",
         "marked_for_delete":true,
         "Domain":{ 
            "id":"default",
            "resource_type":"Domain",
            "marked_for_delete":true,
            "children":[ 
               { 
                  "resource_type":"ChildSecurityPolicy",
                  "marked_for_delete":"false",
                  "SecurityPolicy":{ 
                     "id":"JenkinsAPP01",
                     "resource_type":"SecurityPolicy",
                     "display_name":"JenkinsAPP01",
                     "description":"JenkinsAPP01 webapp Policy",
                     "rules":[ 
                        { 
                           "resource_type":"Rule",
                           "id":"JenkinsAPP01-rule-01",
                           "description":"JenkinsAPP01-rule-01",
                           "display_name":"LB to WEB",
                           "sequence_number":70,
                           "source_groups":[ 
                              "/infra/domains/default/groups/LB"
                           ],
                           "destination_groups":[ 
                              "/infra/domains/default/groups/WEB"
                           ],
                           "services":[ 
                              "/infra/services/HTTPS"
                           ],
                           "profiles":[ 
                              "ANY"
                           ],
                           "action":"ALLOW",
                           "scope":[ 
                              "/infra/domains/default/groups/JenkinsAPP01"
                           ]
                        },
                        { 
                           "resource_type":"Rule",
                           "id":"JenkinsAPP01-rule-02",
                           "description":"JenkinsAPP01-rule-2",
                           "display_name":"WEB to APP",
                           "sequence_number":80,
                           "source_groups":[ 
                              "/infra/domains/default/groups/WEB"
                           ],
                           "destination_groups":[ 
                              "/infra/domains/default/groups/APP"
                           ],
                           "services":[ 
                              "/infra/services/tcp_8443"
                           ],
                           "profiles":[ 
                              "ANY"
                           ],
                           "action":"ALLOW",
                           "scope":[ 
                              "/infra/domains/default/groups/JenkinsAPP01"
                           ]
                        },
                        { 
                           "resource_type":"Rule",
                           "id":"JenkinsAPP01-rule-03",
                           "description":"JenkinsAPP01-rule-03",
                           "display_name":"APP to DB",
                           "sequence_number":90,
                           "source_groups":[ 
                              "/infra/domains/default/groups/APP"
                           ],
                           "destination_groups":[ 
                              "/infra/domains/default/groups/DB"
                           ],
                           "services":[ 
                              "/infra/services/PostgreSQL"
                           ],
                           "profiles":[ 
                              "ANY"
                           ],
                           "action":"ALLOW",
                           "scope":[ 
                              "/infra/domains/default/groups/JenkinsAPP01"
                           ]
                        },
                        { 
                           "resource_type":"Rule",
                           "id":"JenkinsAPP01-rule-04",
                           "description":"JenkinsAPP01-rule-04",
                           "display_name":"DROP",
                           "sequence_number":100,
                           "destination_groups":[ 
                              "ANY"
                           ],
                           "source_groups":[ 
                              "ANY"
                           ],
                           "services":[ 
                              "ANY"
                           ],
                           "profiles":[ 
                              "ANY"
                           ],
                           "action":"DROP",
                           "logged":"true",
                           "scope":[ 
                              "/infra/domains/default/groups/JenkinsAPP01"
                           ]
                        }
                     ]
                  }
               },
               { 
                  "resource_type":"ChildGroup",
                  "Group":{ 
                     "resource_type":"Group",
                     "marked_for_delete":"false",
                     "id":"JenkinsAPP01",
                     "display_name":"JenkinsAPP01",
                     "expression":[ 
                        { 
                           "member_type":"VirtualMachine",
                           "key":"Tag",
                           "operator":"EQUALS",
                           "value":"JenkinsAPP01|",
                           "resource_type":"Condition",
                           "marked_for_delete":"false"
                        }
                     ]
                  }
               },
               { 
                  "resource_type":"ChildGroup",
                  "Group":{ 
                     "resource_type":"Group",
                     "marked_for_delete":true,
                     "id":"LB",
                     "display_name":"LB",
                     "expression":[ 
                        { 
                           "member_type":"VirtualMachine",
                           "key":"Tag",
                           "operator":"EQUALS",
                           "value":"JenkinsAPP01|lb",
                           "resource_type":"Condition",
                           "marked_for_delete":true
                        }
                     ]
                  }
               },
               { 
                  "resource_type":"ChildGroup",
                  "Group":{ 
                     "resource_type":"Group",
                     "marked_for_delete":true,
                     "id":"WEB",
                     "display_name":"WEB",
                     "expression":[ 
                        { 
                           "member_type":"VirtualMachine",
                           "key":"Tag",
                           "operator":"EQUALS",
                           "value":"JenkinsAPP01|web",
                           "resource_type":"Condition",
                           "marked_for_delete":true
                        }
                     ]
                  }
               },
               { 
                  "resource_type":"ChildGroup",
                  "Group":{ 
                     "resource_type":"Group",
                     "marked_for_delete":true,
                     "id":"APP",
                     "display_name":"APP",
                     "expression":[ 
                        { 
                           "member_type":"VirtualMachine",
                           "key":"Tag",
                           "operator":"EQUALS",
                           "value":"JenkinsAPP01|app",
                           "resource_type":"Condition",
                           "marked_for_delete":true
                        }
                     ]
                  }
               },
               { 
                  "resource_type":"ChildGroup",
                  "Group":{ 
                     "resource_type":"Group",
                     "marked_for_delete":true,
                     "id":"DB",
                     "display_name":"DB",
                     "expression":[ 
                        { 
                           "member_type":"VirtualMachine",
                           "key":"Tag",
                           "operator":"EQUALS",
                           "value":"JenkinsAPP01|db",
                           "resource_type":"Condition",
                           "marked_for_delete":true
                        }
                     ]
                  }
               }
            ]
         }
      }
   ]
}
